Machine_Learning_Classes/__init__.py
Machine_Learning_Classes/helper_function.py
AutoAI_patryk_package-0.0.1.dist-info/METADATA
AutoAI_patryk_package-0.0.1.dist-info/WHEEL
AutoAI_patryk_package-0.0.1.dist-info/top_level.txt
AutoAI_patryk_package-0.0.1.dist-info/RECORD
