Metadata-Version: 2.1
Name: AutoAI-patryk-package
Version: 0.0.1
Summary: Auto_AI_patryk
Home-page: UNKNOWN
Author: patryk
License: UNKNOWN
Keywords: python,machine_learning,auto
Platform: UNKNOWN
Classifier: Development Status :: 1 - Planning
Classifier: Intended Audience :: Developers
Classifier: Programming Language :: Python :: 3
Classifier: Operating System :: Unix
Classifier: Operating System :: MacOS :: MacOS X
Classifier: Operating System :: Microsoft :: Windows
